bitsidy_sdk/__init__.py
bitsidy_sdk/sdk.py
bitsidy_sdk-1.0.0.dist-info/METADATA
bitsidy_sdk-1.0.0.dist-info/WHEEL
bitsidy_sdk-1.0.0.dist-info/licenses/LICENSE
bitsidy_sdk-1.0.0.dist-info/RECORD
