Metadata-Version: 2.1
Name: bitsidy-sdk
Version: 1.0.0
Summary: A Python SDK for Bitsidy API
Project-URL: Homepage, https://github.com/bitsidy-com/bitsidy-python-sdk
Project-URL: Issues, https://github.com/bitsidy-com/bitsidy-python-sdk/issues
Author-email: Bitsidy <support@bitsidy.com>
License-Expression: GPL-3.0-or-later
License-File: LICENSE
Classifier: License :: OSI Approved :: GNU General Public License v3 or later (GPLv3+)
Classifier: Operating System :: OS Independent
Classifier: Programming Language :: Python :: 3
Requires-Python: >=3.8
Requires-Dist: cryptography~=42.0.2
Requires-Dist: requests~=2.31.0
